{"id":"index.html","dependencies":[{"name":"./reset.css","dynamic":true,"parent":"/Users/matthewcollier/Documents/Sites/constructor-labs/project-cinema/src/index.html","resolved":"/Users/matthewcollier/Documents/Sites/constructor-labs/project-cinema/src/reset.css"},{"name":"./index.css","dynamic":true,"parent":"/Users/matthewcollier/Documents/Sites/constructor-labs/project-cinema/src/index.html","resolved":"/Users/matthewcollier/Documents/Sites/constructor-labs/project-cinema/src/index.css"},{"name":"./index.js","dynamic":true,"parent":"/Users/matthewcollier/Documents/Sites/constructor-labs/project-cinema/src/index.html","resolved":"/Users/matthewcollier/Documents/Sites/constructor-labs/project-cinema/src/index.js"}],"generated":{"html":"<!DOCTYPE html>\n<html lang=\"en\">\n<head>\n  <meta charset=\"UTF-8\">\n  <meta name=\"viewport\" content=\"width=device-width, initial-scale=1.0\">\n  <meta http-equiv=\"X-UA-Compatible\" content=\"ie=edge\">\n<link rel=\"stylesheet\" type=\"text/css\" href=\"/88fb6fcdefbae231739140276162f50e.css\">\n  <link rel=\"stylesheet\" type=\"text/css\" href=\"/8783648b85c22e04ce8bd7ec454a4438.css\">\n  <title>Document</title>\n</head>\n<body>\n  <div class=\"app\">\n    <header>\n      <h4>Popcorn Time</h4>\n    </header>\n    <nav>\n      <div class=\"navBar\">\n        <div class=\"moviesNav\"><a href=\"#\">Movies</a></div>\n        <div class=\"tvNav\"><a href=\"#\">Tv Series</a></div>\n        <div class=\"genreNav\"><a href=\"#\">Genre</a></div>\n        <div class=\"sortNav\"><a href=\"#\">Sort By</a></div>\n      </div>\n      <div class=\"searchNav\">\n        <form class=\"search\" id=\"search\">\n          <input class=\"search__input\" id=\"search-tf\" name=\"movie\" placeholder=\"Search Movies\" autocomplete=\"city\">\n          <button class=\"btn search__btn\">Go</button>\n        </form>\n      </div>\n    </nav>\n    <main>\n\n    </main>\n  </div>\n  <footer>\n\n  </footer>\n<script src=\"/cf529420afa6fb143ebb7f65cb8403a8.js\"></script>\n</body>\n</html>\n"},"hash":"dc3c15b5ee7203cb6a7991311342066c","cacheData":{}}